LICENSE
MANIFEST.in
README.md
build_requirements.txt
requirements.txt
setup.cfg
setup.py
ferris_cli/__init__.py
ferris_cli/ferris_cli.py
ferris_cli/kafka_handler.pyc
ferris_cli/test.py
ferris_cli.egg-info/PKG-INFO
ferris_cli.egg-info/SOURCES.txt
ferris_cli.egg-info/dependency_links.txt
ferris_cli.egg-info/not-zip-safe
ferris_cli.egg-info/requires.txt
ferris_cli.egg-info/top_level.txt
ferris_cli/__pycache__/ferris_cli.cpython-36.pyc
ferris_cli/__pycache__/ferris_cli.cpython-38.pyc
ferris_cli/v2/__init__.py
ferris_cli/v2/services/__init__.py
ferris_cli/v2/services/broker.py
ferris_cli/v2/services/config.py
ferris_cli/v2/services/events.py
ferris_cli/v2/services/logging.py
ferris_cli/v2/services/metrics.py
ferris_cli/v2/services/notifications.py
ferris_cli/v2/services/oidc.py
ferris_cli/v2/services/postgres.py
ferris_cli/v2/services/search.py
ferris_cli/v2/services/storage.py
ferris_cli/v2/services/storageS3.py